imgtool/__init__.py
imgtool/boot_record.py
imgtool/dumpinfo.py
imgtool/image.py
imgtool/main.py
imgtool/version.py
imgtool/keys/__init__.py
imgtool/keys/ecdsa.py
imgtool/keys/ed25519.py
imgtool/keys/general.py
imgtool/keys/privatebytes.py
imgtool/keys/rsa.py
imgtool/keys/x25519.py
imgtool-2.3.0.dist-info/METADATA
imgtool-2.3.0.dist-info/WHEEL
imgtool-2.3.0.dist-info/entry_points.txt
imgtool-2.3.0.dist-info/top_level.txt
imgtool-2.3.0.dist-info/RECORD
