Metadata-Version: 2.1
Name: imgtool
Version: 2.3.0
Summary: MCUboot's image signing and key management
Home-page: http://github.com/mcu-tools/mcuboot
Author: The MCUboot committers
Author-email: mcuboot@groups.io
License: Apache Software License
Classifier: Programming Language :: Python :: 3
Classifier: Development Status :: 4 - Beta
Classifier: Topic :: Software Development :: Build Tools
Classifier: License :: OSI Approved :: Apache Software License
Requires-Python: >=3.6
Requires-Dist: cbor2
Requires-Dist: click
Requires-Dist: cryptography >=40.0.0
Requires-Dist: intelhex >=2.2.1
Requires-Dist: pyyaml
